bennellickeng.kitdrivers-2018.4-py3.6-nspkg.pth
bennellickeng/kitdrivers/__init__.py
bennellickeng/kitdrivers/positioner/__init__.py
bennellickeng/kitdrivers/positioner/positioner.py
bennellickeng/kitdrivers/prologix/__init__.py
bennellickeng/kitdrivers/prologix/prologix.py
bennellickeng/kitdrivers/prologix/vna.py
bennellickeng/kitdrivers/rands/__init__.py
bennellickeng/kitdrivers/rands/vna.py
bennellickeng/kitdrivers/usbtmc/__init__.py
bennellickeng/kitdrivers/usbtmc/dc_load_array_3720a.py
bennellickeng/kitdrivers/usbtmc/multimeter_dmm6500.py
bennellickeng/kitdrivers/usbtmc/psu.py
bennellickeng/kitdrivers/usbtmc/scope.py
bennellickeng/kitdrivers/usbtmc/siggen.py
bennellickeng/kitdrivers/usbtmc/usbtmc.py
bennellickeng/kitdrivers/vna/__init__.py
bennellickeng/kitdrivers/vna/pseudovna.py
bennellickeng/kitdrivers/vna/view.py
bennellickeng.kitdrivers-2018.4.dist-info/METADATA
bennellickeng.kitdrivers-2018.4.dist-info/RECORD
bennellickeng.kitdrivers-2018.4.dist-info/WHEEL
bennellickeng.kitdrivers-2018.4.dist-info/entry_points.txt
bennellickeng.kitdrivers-2018.4.dist-info/namespace_packages.txt
bennellickeng.kitdrivers-2018.4.dist-info/top_level.txt
