Metadata-Version: 2.1
Name: bennellickeng.kitdrivers
Version: 2018.4
Summary: Bennellick Engineering Kit Drivers
Home-page: https://bitbucket.org/bennellickeng/kit-drivers/
Author: Bennellick Engineering Limited
Author-email: info@bennellick.com
License: BSD 3-clause
Platform: UNKNOWN
Classifier: Programming Language :: Python :: 3
Classifier: Programming Language :: Python :: 3.5
Classifier: Programming Language :: Python :: 3.6
Classifier: Programming Language :: Python :: 3.7
Classifier: License :: OSI Approved :: BSD License
Classifier: Operating System :: POSIX :: Linux
Requires-Dist: boltons (>=17.0.0)
Requires-Dist: numpy
Requires-Dist: scikit-rf (>=0.14.0)
Requires-Dist: matplotlib
Requires-Dist: pyudev
